minimum_dependencies/__init__.py
minimum_dependencies/_core.py
minimum_dependencies/_script.py
minimum_dependencies/_version.py
minimum_dependencies/tests/__init__.py
minimum_dependencies/tests/test_core.py
minimum_dependencies/tests/test_script.py
minimum_dependencies-0.1.0.dist-info/LICENSE
minimum_dependencies-0.1.0.dist-info/METADATA
minimum_dependencies-0.1.0.dist-info/WHEEL
minimum_dependencies-0.1.0.dist-info/entry_points.txt
minimum_dependencies-0.1.0.dist-info/top_level.txt
minimum_dependencies-0.1.0.dist-info/RECORD
