Metadata-Version: 2.1
Name: minimum-dependencies
Version: 0.1.0
Summary: Get the minimum dependencies of a Python package
Author-email: William Jamieson <help@stsci.edu>
License: BSD 3-Clause License
Classifier: License :: OSI Approved :: BSD License
Classifier: Programming Language :: Python
Classifier: Programming Language :: Python :: 3
Classifier: Programming Language :: Python :: 3.8
Classifier: Programming Language :: Python :: 3.9
Classifier: Programming Language :: Python :: 3.10
Classifier: Programming Language :: Python :: 3.11
Classifier: Development Status :: 5 - Production/Stable
Requires-Python: >=3.8
License-File: LICENSE
Requires-Dist: importlib-metadata (>=4.11.4)
Requires-Dist: packaging (>=23)
Requires-Dist: requests (>=2.25)
Provides-Extra: other
Requires-Dist: astropy[all] (>=5) ; extra == 'other'
Provides-Extra: test
Requires-Dist: pytest (>=6) ; extra == 'test'
Requires-Dist: pytest-doctestplus (>=0.12) ; extra == 'test'
